sakura/__init__.py
sakura/config.yml
sakura/functional.py
sakura/ml/__init__.py
sakura/ml/async_trainer.py
sakura/ml/sakura_trainer.py
sakura/ml/epoch/__init__.py
sakura/ml/epoch/range.py
sakura_ml-0.1.1.dist-info/METADATA
sakura_ml-0.1.1.dist-info/WHEEL
sakura_ml-0.1.1.dist-info/entry_points.txt
sakura_ml-0.1.1.dist-info/top_level.txt
sakura_ml-0.1.1.dist-info/RECORD
