Metadata-Version: 2.1
Name: sakura-ml
Version: 0.1.1
Summary: Sakura provides asynchronous training for DNN.
Home-page: https://zakuro.ai
Author: ZakuroAI
Author-email: git@zakuro.ai
License: MIT
Platform: linux_debian_10_x86_64
Classifier: Programming Language :: Python :: 3
Classifier: License :: OSI Approved :: MIT License
Requires-Python: >=3.6
Requires-Dist: tqdm (>=4.64.0)
Requires-Dist: torch
Requires-Dist: torchvision
Requires-Dist: numpy
Requires-Dist: gnutools-python
Requires-Dist: mpi4py
Requires-Dist: six
Requires-Dist: bson
